repeng/__init__.py
repeng/control.py
repeng/extract.py
repeng/saes.py
repeng/tests.py
repeng-0.4.0.dist-info/METADATA
repeng-0.4.0.dist-info/WHEEL
repeng-0.4.0.dist-info/licenses/LICENSE
repeng-0.4.0.dist-info/RECORD
