Metadata-Version: 2.3
Name: repeng
Version: 0.4.0
Summary: representation engineering / control vectors
Author-email: Theia Vogel <theia@vgel.me>
Requires-Python: >=3.10
Requires-Dist: gguf>=0.6.0
Requires-Dist: numpy<2.0.0
Requires-Dist: scikit-learn>=1.4.0
Requires-Dist: torch>=2.1.2
Requires-Dist: tqdm>=4.66.1
Requires-Dist: transformers>=4.36.2
